Workbook

Sheet Export Summary
B3: This document was exported from Numbers. Each table was converted to an Excel worksheet. All other objects on each Numbers sheet were placed on separate worksheets. Please be aware that formula calculations may differ in Excel.
B7: Numbers Sheet Name | C7: Numbers Table Name | D7: Excel Worksheet Name
B9: README
C10: Table 1 | D10: README
B11: Rubric
C12: Table 1 | D12: Rubric
B13: CSF Scoring
C14: Table 1 | D14: CSF Scoring
B15: Findings
C16: Table 1 | D16: Findings
B17: Dashboard
C18: Table 1 | D18: Dashboard

Sheet README
B2: NIST CSF 2.0 Maturity Assessment — Scoring Workbook
B3: Subject organization: Meridian Bridge Capital (MBC) — fictional fintech lender
B5: Purpose
B6: This workbook is the scoring engine for a self-assessment against NIST CSF 2.0. It contains all 106 subcategories across the six functions (Govern, Identify, Protect, Detect, Respond, Recover), with structured columns for current tier, target tier, gap, and evidence. The Dashboard tab summarizes maturity at the function level using formulas — no manual rollup needed.
B8: How to use this workbook
B9: 1. Read the Rubric tab
B10: Understand the 1-4 tier scale before scoring.
B11: 2. Go to the CSF Scoring tab
B12: All 106 subcategories are listed, grouped by function.
B13: 3. For each subcategory
B14: Read the description, identify evidence at MBC, score Current Tier (1-4).
B15: 4. Set Target Tier
... B27: Subcategory IDs and descriptions in this workbook are paraphrased from the NIST CSF 2.0 Core (published Feb 26, 2024). Before producing final deliverables, validate all subcategory text against the official NIST CSF 2.0 Core spreadsheet, available free at https://www.nist.gov/cyberframework/framework

Sheet Rubric
B2: Scoring Rubric — NIST CSF 2.0 Implementation Tiers
B4: Tier | C4: Name | D4: Definition | E4: Typical evidence
B5: 1 | C5: Partial | D5: Practices are ad hoc and reactive. No documented procedures. Risk awareness exists informally if at all. | E5: Verbal confirmation only; no artifacts
B6: 2 | C6: Risk Informed | D6: Awareness exists. Practices are performed but inconsistently or without formal documentation. May be in transition. | E6: Drafts, informal runbooks, partial coverage
B7: 3 | C7: Repeatable | D7: Documented practices applied consistently. Owners are named. Reviewed periodically. | E7: Approved policies, defined procedures, evidence of execution
B8: 4 | C8: Adaptive | D8: Practices continuously improved based on threat intelligence, metrics, and lessons learned. Integrated across enterprise risk. | E8: Metrics tracked, improvement cycles documented, threat-informed adjustments
B11: Scoring guidance
B12: • Score current tier based on observed evidence at MBC today, not what's planned.
B13: • When evidence is mixed across tiers, pick the lowest tier that fully fits.
B14: • Target tier should reflect risk appetite, regulatory drivers, and business context — not aspiration.
B15: • Target tier need not be 4 for every subcategory. Tier 3 (Repeatable) is appropriate for many areas.
B16: • Gap = Target − Current. Any positive gap is a candidate finding.
B17: • Document evidence specifically: 'Policy XYZ approved in Q1 2025, last reviewed March 2026' beats 'Policy exists.'

Sheet CSF Scoring
A1: Function | B1: Code | C1: Category | D1: Cat Code | E1: Subcategory ID | F1: Subcategory Description | G1: Current Tier | H1: Target Tier | I1: Gap | J1: Evidence / Observations | K1: Finding ID | L1: Status
A2: Govern | B2: GV | C2: Organizational Context | D2: GV.OC | E2: GV.OC-01 | F2: The organizational mission is understood and informs cybersecurity risk management | G2: 2 | H2: 3 | I2: {=IF(AND(ISNUMBER(G2),ISNUMBER(H2)),H2-G2,"")} -> 1 | J2: Leadership demonstrates awareness of MBC's lending mission and funds compliance initiatives (SOC 2 Type I done, Type II in progress; FTC Safeguards work underway; GLBA advisory completed). However, no formal cybersecurity steering committee exists, cybersecurity is not a standing ELT agenda item, and no documented cybersecurity strategy explicitly links to the mission. Connection is implicit rather than formalized.
A3: Govern | B3: GV | C3: Organizational Context | D3: GV.OC | E3: GV.OC-02 | F3: Internal and external stakeholders' cybersecurity needs and expectations are understood and considered | G3: 2 | H3: 3 | I3: {=IF(AND(ISNUMBER(G3),ISNUMBER(H3)),H3-G3,"")} -> 1 | J3: MBC reactively addresses stakeholder needs as they arise, SOC 2 Type II in progress per capital partner request, state regulator information requests handled by Compliance, board attention driven by industry breaches. No documented stakeholder map or systematic process to anticipate and integrate expectations into the cybersecurity strategy. Compliance team's regulatory tracker (Smartsheet) covers regulatory stakeholders but not capital partners, customers, or vendors.
A4: Govern | B4: GV | C4: Organizational Context | D4: GV.OC | E4: GV.OC-03 | F4: Legal, regulatory, and contractual cybersecurity requirements (including privacy and civil liberties) are understood and managed | G4: 3 | H4: 3 | I4: {=IF(AND(ISNUMBER(G4),ISNUMBER(H4)),H4-G4,"")} -> 0 | J4: Compliance team (3 FTE) maintains regulatory compliance tracker in Smartsheet covering GLBA, FTC Safeguards, FCRA, BSA/AML, state lending licenses (20+ states), CCPA/CPRA, TILA/RESPA/TRID, and NMLS obligations. External GLBA advisory completed mid-2025. FTC Safeguards Rule program in progress with designated QI and draft ISP (pending board approval). Gap: ISP not yet board-approved; no formal security clause review process for new contracts.
A5: Govern | B5: GV | C5: Organizational Context | D5: GV.OC | E5: GV.OC-04 | F5: Critical objectives, capabilities, and services that external stakeholders depend on are understood and communicated | G5: 3 | H5: 3 | I5: {=IF(AND(ISNUMBER(G5),ISNUMBER(H5)),H5-G5,"")} -> 0 | J5: MBC understands key external dependencies — DR plan documents recovery prioritization (borrower portal → LOS API → admin tools → analytics) with business input. Customer-facing status page (status.meridianbridge.example) communicates service status. Capital partner reporting cadence operational. Gaps: no formal external commitments register, no published SLAs to borrowers, broader service obligations not systematically documented beyond DR scope.
A6: Govern | B6: GV | C6: Organizational Context | D6: GV.OC | E6: GV.OC-05 | F6: Outcomes, capabilities, and services that the organization depends on are understood and communicated | G6: 2 | H6: 3 | I6: {=IF(AND(ISNUMBER(G6),ISNUMBER(H6)),H6-G6,"")} -> 1 | J6: Technical dependencies (AWS, Okta, Salesforce, Plaid, credit bureaus) are known and their status monitored via Datadog and manual status page checks. However, no central vendor inventory exists — vendors tracked across bill.com (finance), a Legal Google Sheet, and DocuSign CLM with no master view. No criticality tiering applied. Compliance team aware of regulatory partner dependencies but not integrated with technology dependency mapping.
A7: Govern | B7: GV | C7: Risk Management Strategy | D7: GV.RM | E7: GV.RM-01 | F7: Risk management objectives are established and agreed to by organizational stakeholders | G7: 2 | H7: 3 | I7: {=IF(AND(ISNUMBER(G7),ISNUMBER(H7)),H7-G7,"")} -> 1 | J7: Implicit risk management objectives exist around achieving SOC 2 Type II and FTC Safeguards compliance, surfaced through CTO/Director of InfoSec conversations. No documented set of risk management objectives formally agreed by leadership. Compliance team maintains a regulatory tracker but it covers obligations, not risk management objectives. Notion-based informal risk list (~30 items, updated 6 weeks ago) is not stakeholder-approved.
A8: Govern | B8: GV | C8: Risk Management Strategy | D8: GV.RM | E8: GV.RM-02 | F8: Risk appetite and risk tolerance statements are established, communicated, and maintained | G8: 1 | H8: 3 | I8: {=IF(AND(ISNUMBER(G8),ISNUMBER(H8)),H8-G8,"")} -> 2 | J8: Risk appetite and tolerance statements are undocumented. Implicit signals exist via leadership behavior (funded SOC 2, Safeguards Rule work, GLBA advisory) but no formal statements have been drafted, communicated, or maintained. No documented thresholds for risk acceptance or escalation.
A9: Govern | B9: GV | C9: Risk Management Strategy | D9: GV.RM | E9: GV.RM-03 | F9: Cybersecurity risk management activities and outcomes are included in enterprise risk management processes | G9: 1 | H9: 3 | I9: {=IF(AND(ISNUMBER(G9),ISNUMBER(H9)),H9-G9,"")} -> 2 | J9: No formal enterprise risk management process exists at MBC. Cybersecurity risks tracked separately in a Notion page; regulatory compliance tracked in Smartsheet by the Compliance team; no unified ERM view. Board's Audit Committee reviews cybersecurity annually unless incident warrants. Cybersecurity not integrated into broader risk management processes.
A10: Govern | B10: GV | C10: Risk Management Strategy | D10: GV.RM | E10: GV.RM-04 | F10: Strategic direction describing appropriate risk response options is established and communicated | G10: 1 | H10: 3 | I10: {=IF(AND(ISNUMBER(G10),ISNUMBER(H10)),H10-G10,"")} -> 2 | J10: No documented risk response strategy or framework defining when to mitigate, transfer, avoid, or accept cybersecurity risks. Decisions made case-by-case by CTO and Director of InfoSec. Mandiant IR retainer (a risk transfer mechanism) exists but is currently expired without renewal — illustrative of unmanaged risk response posture. No communicated strategic direction to managers and practitioners.
A11: Govern | B11: GV | C11: Risk Management Strategy | D11: GV.RM | E11: GV.RM-05 | F11: Lines of communication across the organization are established for cybersecurity risks, including supplier and third-party risks | G11: 2 | H11: 3 | I11: {=IF(AND(ISNUMBER(G11),ISNUMBER(H11)),H11-G11,"")} -> 1 | J11: Informal communication channels exist: Director of InfoSec attends monthly ELT meetings (ad hoc agenda), PagerDuty creates Slack incident channels for incidents. No documented communication framework defining escalation paths, frequency, or content. Third-party risk communication weak: Legal handles vendor diligence during contracting without consistent InfoSec coordination. No formal supplier risk communication channels established.
A12: Govern | B12: GV | C12: Risk Management Strategy | D12: GV.RM | E12: GV.RM-06 | F12: A standardized method for calculating, documenting, categorizing, and prioritizing cybersecurity risks is established and communicated | G12: 1 | H12: 3 | I12: {=IF(AND(ISNUMBER(G12),ISNUMBER(H12)),H12-G12,"")} -> 2 | J12: No standardized cybersecurity risk methodology. Informal Notion risk list (~30 items) lacks consistent severity scoring, likelihood/impact calculation, or categorization. Last updated 6 weeks ago. Incident severity scale (Sev1-4) defined in IR plan but applies to incidents post-occurrence, not to forward-looking risk assessment. No documented method communicated to managers or practitioners.
A13: Govern | B13: GV | C13: Risk Management Strategy | D13: GV.RM | E13: GV.RM-07 | F13: Strategic opportunities (positive risks) are characterized and included in cybersecurity risk discussions | G13: 1 | H13: 2 | I13: {=IF(AND(ISNUMBER(G13),ISNUMBER(H13)),H13-G13,"")} -> 1 | J13: Positive risks (strategic opportunities from cybersecurity investment) not formally characterized or discussed. SOC 2 Type II implicitly viewed as a business enabler (capital partner relationships, future fundraise readiness) but framed as compliance obligation, not opportunity. Practice does not exist in formalized form.
... A20: Govern | B20: GV | C20: Oversight | D20: GV.OV | E20: GV.OV-01 | F20: Cybersecurity risk management strategy outcomes are reviewed to inform and adjust strategy and direction | G20: 2 | H20: 3 | I20: {=IF(AND(ISNUMBER(G20),ISNUMBER(H20)),H20-G20,"")} -> 1 | J20: Strategic adjustments observable in response to changing requirements: FTC Safeguards Rule compliance project, SOC 2 Type II push driven by capital partner expectations, increased board attention following industry breaches. However, no documented strategy review process exists. Adjustments are reactive and project-based rather than emerging from a structured review of coverage gaps.
A21: Govern | B21: GV | C21: Oversight | D21: GV.OV | E21: GV.OV-02 | F21: The cybersecurity risk management strategy is reviewed and adjusted to ensure coverage of organizational requirements and risks | I21: {=IF(AND(ISNUMBER(G21),ISNUMBER(H21)),H21-G21,"")}
A22: Govern | B22: GV | C22: Oversight | D22: GV.OV | E22: GV.OV-03 | F22: Organizational cybersecurity risk management performance is evaluated and reviewed for adjustments needed | I22: {=IF(AND(ISNUMBER(G22),ISNUMBER(H22)),H22-G22,"")}
A23: Govern | B23: GV | C23: Cybersecurity Supply Chain Risk Management | D23: GV.SC | E23: GV.SC-01 | F23: A C-SCRM program, strategy, objectives, policies, and processes are established and agreed to by stakeholders | I23: {=IF(AND(ISNUMBER(G23),ISNUMBER(H23)),H23-G23,"")}
A24: Govern | B24: GV | C24: Cybersecurity Supply Chain Risk Management | D24: GV.SC | E24: GV.SC-02 | F24: Cybersecurity roles and responsibilities for suppliers, customers, and partners are established, communicated, and coordinated | I24: {=IF(AND(ISNUMBER(G24),ISNUMBER(H24)),H24-G24,"")}
A25: Govern | B25: GV | C25: Cybersecurity Supply Chain Risk Management | D25: GV.SC | E25: GV.SC-03 | F25: C-SCRM is integrated into cybersecurity and enterprise risk management, risk assessment, and improvement processes | I25: {=IF(AND(ISNUMBER(G25),ISNUMBER(H25)),H25-G25,"")}
A26: Govern | B26: GV | C26: Cybersecurity Supply Chain Risk Management | D26: GV.SC | E26: GV.SC-04 | F26: Suppliers are known and prioritized by criticality | I26: {=IF(AND(ISNUMBER(G26),ISNUMBER(H26)),H26-G26,"")}
A27: Govern | B27: GV | C27: Cybersecurity Supply Chain Risk Management | D27: GV.SC | E27: GV.SC-05 | F27: Requirements to address cybersecurity risks in supply chains are established, prioritized, and integrated into contracts | I27: {=IF(AND(ISNUMBER(G27),ISNUMBER(H27)),H27-G27,"")}
A28: Govern | B28: GV | C28: Cybersecurity Supply Chain Risk Management | D28: GV.SC | E28: GV.SC-06 | F28: Planning and due diligence are performed to reduce risks before entering into supplier or other third-party relationships | I28: {=IF(AND(ISNUMBER(G28),ISNUMBER(H28)),H28-G28,"")}
A29: Govern | B29: GV | C29: Cybersecurity Supply Chain Risk Management | D29: GV.SC | E29: GV.SC-07 | F29: Risks posed by suppliers, their products/services, and third parties are recorded, prioritized, assessed, responded to, and monitored | I29: {=IF(AND(ISNUMBER(G29),ISNUMBER(H29)),H29-G29,"")}
A30: Govern | B30: GV | C30: Cybersecurity Supply Chain Risk Management | D30: GV.SC | E30: GV.SC-08 | F30: Relevant suppliers and third parties are included in incident planning, response, and recovery activities | I30: {=IF(AND(ISNUMBER(G30),ISNUMBER(H30)),H30-G30,"")}
A31: Govern | B31: GV | C31: Cybersecurity Supply Chain Risk Management | D31: GV.SC | E31: GV.SC-09 | F31: Supply chain security practices are integrated into cybersecurity and ERM programs, with performance monitored across product/service lifecycles | I31: {=IF(AND(ISNUMBER(G31),ISNUMBER(H31)),H31-G31,"")}
A32: Govern | B32: GV | C32: Cybersecurity Supply Chain Risk Management | D32: GV.SC | E32: GV.SC-10 | F32: C-SCRM plans include provisions for activities that occur after the conclusion of a partnership or service agreement | I32: {=IF(AND(ISNUMBER(G32),ISNUMBER(H32)),H32-G32,"")}
... A107: Recover | B107: RC | C107: Incident Recovery Communication | D107: RC.CO | E107: RC.CO-04 | F107: Public updates on incident recovery are properly shared using approved methods and messaging | I107: {=IF(AND(ISNUMBER(G107),ISNUMBER(H107)),H107-G107,"")}

Sheet Findings
A1: Finding ID | B1: Title | C1: Function | D1: Subcategory IDs | E1: Current State | F1: Risk | G1: Recommendation | H1: Severity (1-5) | I1: Effort (S/M/L/XL) | J1: Priority | K1: Phase | L1: Owner | M1: Status
A2: F-01 | B2: No formal cybersecurity supply chain risk management program | C2: Govern | D2: GV.SC-01, GV.SC-04, GV.SC-07 | E2: MBC has 80+ third-party vendors but no central inventory, no tiering by criticality, and no recurring re-assessment cadence. Initial diligence is performed informally by Legal during contracting. | F2: Critical vendor compromises (e.g., LOS plugins, credit bureau APIs) could go undetected and unmitigated. Likely failure point for FTC Safeguards Rule audit and SOC 2 Type II. | G2: Stand up a formal vendor risk management program: vendor inventory with criticality tiering, security questionnaire library, contractual security clauses, annual re-assessment for Tier 1 vendors. | H2: 5 | I2: L | J2: High | K2: Phase 1 | L2: Director of InfoSec | M2: Open
A3: F-02 | B3: Privileged access reviews performed ad hoc, not on documented cadence | C3: Protect | D3: PR.AA-05 | E3: Admin access to AWS, Salesforce, and the LOS is granted as needed but reviewed only when an audit prompts it. No quarterly access certification process exists. | F3: Stale privileged access creates insider threat and audit findings. SOC 2 Type II auditors will flag this as a control deficiency. | G3: Implement quarterly privileged access reviews. Use Okta + AWS IAM Access Analyzer to generate review lists. Document approver, review date, action taken per account. | H3: 4 | I3: M | J3: High | K3: Phase 1 | L3: Security Engineer | M3: Open
A4: ↑ Two sample findings above (light blue tint) are illustrative. Replace with your own as you score the subcategories.

Sheet Dashboard
B2: Maturity Dashboard
B3: Auto-calculated from the CSF Scoring tab. Updates as you score subcategories.
B5: Function-Level Maturity
B6: Code | C6: Function | D6: Avg Current | E6: Avg Target | F6: Avg Gap | G6: % Scored | H6: Description
B7: GV | C7: Govern | D7: {=_xlfn.IFERROR(_xlfn.AVERAGEIF('CSF Scoring'!B1:B107,"GV",'CSF Scoring'!G1:G107),"")} -> 1.7894737 | E7: {=_xlfn.IFERROR(_xlfn.AVERAGEIF('CSF Scoring'!B1:B107,"GV",'CSF Scoring'!H1:H107),"")} -> 2.9473684 | F7: {=_xlfn.IFERROR(_xlfn.AVERAGEIF('CSF Scoring'!B1:B107,"GV",'CSF Scoring'!I1:I107),"")} -> 1.1578947 | G7: {=_xlfn.COUNTIFS('CSF Scoring'!B1:B107,"GV",'CSF Scoring'!G1:G107,">0")/COUNTIF('CSF Scoring'!B1:B107,"GV")} -> 0.61290323 | H7: Establish, communicate, and monitor the organization's cybersecurity risk management strategy, expectations, and policy
B8: ID | C8: Identify | D8: {=_xlfn.IFERROR(_xlfn.AVERAGEIF('CSF Scoring'!B1:B107,"ID",'CSF Scoring'!G1:G107),"")} | E8: {=_xlfn.IFERROR(_xlfn.AVERAGEIF('CSF Scoring'!B1:B107,"ID",'CSF Scoring'!H1:H107),"")} | F8: {=_xlfn.IFERROR(_xlfn.AVERAGEIF('CSF Scoring'!B1:B107,"ID",'CSF Scoring'!I1:I107),"")} | G8: {=_xlfn.COUNTIFS('CSF Scoring'!B1:B107,"ID",'CSF Scoring'!G1:G107,">0")/COUNTIF('CSF Scoring'!B1:B107,"ID")} -> 0 | H8: Help determine the current cybersecurity risk to the organization
B9: PR | C9: Protect | D9: {=_xlfn.IFERROR(_xlfn.AVERAGEIF('CSF Scoring'!B1:B107,"PR",'CSF Scoring'!G1:G107),"")} | E9: {=_xlfn.IFERROR(_xlfn.AVERAGEIF('CSF Scoring'!B1:B107,"PR",'CSF Scoring'!H1:H107),"")} | F9: {=_xlfn.IFERROR(_xlfn.AVERAGEIF('CSF Scoring'!B1:B107,"PR",'CSF Scoring'!I1:I107),"")} | G9: {=_xlfn.COUNTIFS('CSF Scoring'!B1:B107,"PR",'CSF Scoring'!G1:G107,">0")/COUNTIF('CSF Scoring'!B1:B107,"PR")} -> 0 | H9: Use safeguards to prevent or reduce cybersecurity risk
B10: DE | C10: Detect | D10: {=_xlfn.IFERROR(_xlfn.AVERAGEIF('CSF Scoring'!B1:B107,"DE",'CSF Scoring'!G1:G107),"")} | E10: {=_xlfn.IFERROR(_xlfn.AVERAGEIF('CSF Scoring'!B1:B107,"DE",'CSF Scoring'!H1:H107),"")} | F10: {=_xlfn.IFERROR(_xlfn.AVERAGEIF('CSF Scoring'!B1:B107,"DE",'CSF Scoring'!I1:I107),"")} | G10: {=_xlfn.COUNTIFS('CSF Scoring'!B1:B107,"DE",'CSF Scoring'!G1:G107,">0")/COUNTIF('CSF Scoring'!B1:B107,"DE")} -> 0 | H10: Find and analyze possible cybersecurity attacks and compromises
B11: RS | C11: Respond | D11: {=_xlfn.IFERROR(_xlfn.AVERAGEIF('CSF Scoring'!B1:B107,"RS",'CSF Scoring'!G1:G107),"")} | E11: {=_xlfn.IFERROR(_xlfn.AVERAGEIF('CSF Scoring'!B1:B107,"RS",'CSF Scoring'!H1:H107),"")} | F11: {=_xlfn.IFERROR(_xlfn.AVERAGEIF('CSF Scoring'!B1:B107,"RS",'CSF Scoring'!I1:I107),"")} | G11: {=_xlfn.COUNTIFS('CSF Scoring'!B1:B107,"RS",'CSF Scoring'!G1:G107,">0")/COUNTIF('CSF Scoring'!B1:B107,"RS")} -> 0 | H11: Take action regarding a detected cybersecurity incident
B12: RC | C12: Recover | D12: {=_xlfn.IFERROR(_xlfn.AVERAGEIF('CSF Scoring'!B1:B107,"RC",'CSF Scoring'!G1:G107),"")} | E12: {=_xlfn.IFERROR(_xlfn.AVERAGEIF('CSF Scoring'!B1:B107,"RC",'CSF Scoring'!H1:H107),"")} | F12: {=_xlfn.IFERROR(_xlfn.AVERAGEIF('CSF Scoring'!B1:B107,"RC",'CSF Scoring'!I1:I107),"")} | G12: {=_xlfn.COUNTIFS('CSF Scoring'!B1:B107,"RC",'CSF Scoring'!G1:G107,">0")/COUNTIF('CSF Scoring'!B1:B107,"RC")} -> 0 | H12: Restore assets and operations affected by a cybersecurity incident
B13: ALL | C13: Overall | D13: {=_xlfn.IFERROR(AVERAGE('CSF Scoring'!G2:G107),"")} -> 1.7894737 | E13: {=_xlfn.IFERROR(AVERAGE('CSF Scoring'!H2:H107),"")} -> 2.9473684 | F13: {=_xlfn.IFERROR(AVERAGE('CSF Scoring'!I2:I107),"")} -> 1.1578947 | G13: {=COUNTIF('CSF Scoring'!G2:G107,">0")/106} -> 0.17924528 | H13: Across all 106 subcategories
B15: Gap Distribution
B16: Gap Size | C16: Meaning | D16: Count | E16: % of Total
B17: 0 | C17: On target — no action | D17: {=COUNTIF('CSF Scoring'!I2:I107,0)} -> 2 | E17: {=_xlfn.IFERROR(D17/COUNT('CSF Scoring'!I2:I107),"")} -> 0.10526316
B18: 1 | C18: Minor gap — single tier | D18: {=COUNTIF('CSF Scoring'!I2:I107,1)} -> 12 | E18: {=_xlfn.IFERROR(D18/COUNT('CSF Scoring'!I2:I107),"")} -> 0.63157895
B19: 2 | C19: Moderate gap — two tiers | D19: {=COUNTIF('CSF Scoring'!I2:I107,2)} -> 5 | E19: {=_xlfn.IFERROR(D19/COUNT('CSF Scoring'!I2:I107),"")} -> 0.26315789
B20: 3 | C20: Major gap — three tiers | D20: {=COUNTIF('CSF Scoring'!I2:I107,3)} -> 0 | E20: {=_xlfn.IFERROR(D20/COUNT('CSF Scoring'!I2:I107),"")} -> 0
B22: Current Tier Distribution
B23: Tier | C23: Name | D23: Count | E23: % of Scored
B24: 1 | C24: Partial | D24: {=COUNTIF('CSF Scoring'!G2:G107,1)} -> 6 | E24: {=_xlfn.IFERROR(D24/COUNT('CSF Scoring'!G2:G107),"")} -> 0.31578947
B25: 2 | C25: Risk Informed | D25: {=COUNTIF('CSF Scoring'!G2:G107,2)} -> 11 | E25: {=_xlfn.IFERROR(D25/COUNT('CSF Scoring'!G2:G107),"")} -> 0.57894737
B26: 3 | C26: Repeatable | D26: {=COUNTIF('CSF Scoring'!G2:G107,3)} -> 2 | E26: {=_xlfn.IFERROR(D26/COUNT('CSF Scoring'!G2:G107),"")} -> 0.10526316
B27: 4 | C27: Adaptive | D27: {=COUNTIF('CSF Scoring'!G2:G107,4)} -> 0 | E27: {=_xlfn.IFERROR(D27/COUNT('CSF Scoring'!G2:G107),"")} -> 0
